Metadata-Version: 2.4
Name: adafruit-circuitpython-argv-file
Version: 1.0.1
Summary: Pass arguments to code files by writing them to a file before launching.
Author-email: Adafruit Industries <circuitpython@adafruit.com>
License: MIT
Project-URL: Homepage, https://github.com/adafruit/Adafruit_CircuitPython_Argv_File
Keywords: adafruit,blinka,circuitpython,micropython,argv_file,arguments,args,argv,values,variables,configuration,pass,passing,files,json
Classifier: Intended Audience :: Developers
Classifier: Topic :: Software Development :: Libraries
Classifier: Topic :: Software Development :: Embedded Systems
Classifier: Topic :: System :: Hardware
Classifier: License :: OSI Approved :: MIT License
Classifier: Programming Language :: Python :: 3
License-File: LICENSE
Requires-Dist: Adafruit-Blinka
Requires-Dist: Adafruit-CircuitPython-Pathlib
Provides-Extra: optional
Dynamic: license-file
